tests/__init__.py
tests/meower.py
gdreq-0.0.1.dist-info/LICENSE
gdreq-0.0.1.dist-info/METADATA
gdreq-0.0.1.dist-info/WHEEL
gdreq-0.0.1.dist-info/top_level.txt
gdreq-0.0.1.dist-info/RECORD
