Metadata-Version: 2.1
Name: gdreq
Version: 0.0.1
Summary: A library for sending requests to the Geometry Dash servers
Author: NumbersTada
Author-email: NumbersTada <tadaktatak61@gmail.com>
Classifier: Programming Language :: Python :: 3
Classifier: License :: OSI Approved :: MIT License
Classifier: Operating System :: OS Independent
Requires-Python: >=3.6
License-File: LICENSE
